[
  {
    "albumName": "Eveniment anibversar desfasurat la Sala de marmura a Cercului Militar National Bucuresti.",
    "date": "12 mai 2022",
    "imgPath": "./img/12_mai_2022/12_mai_2022_01.jpg",
    "fotoDescription": "",
    "description": "12 mai 2022 Cu prilejul “Anului Smaranda Braescu” Statul Major al Fortelor Aeriene a organizat evenimentul aniversar national, cu sprijinul nemijlocit al Asociatiei Romane pentru Propaganda si Istoria Aeronauticii “Smaranda Braescu”. <br/> Evenimentul s-a desfasurat la Sala de marmura a Cercului Militar National Bucuresti. Au participat reprezentanti ai guvernului Romaniei, ai misiunilor militare acreditate la Bucuresti, istorici, personalitati ale Aviatiei Romane, membrii ARPIA.",
    "about": ""
  },
  {
    "imgPath": "./img/12_mai_2022/12_mai_2022_02.jpg"
  },
  {
    "imgPath": "./img/12_mai_2022/12_mai_2022_03.jpg"
  },
  {
    "imgPath": "./img/12_mai_2022/12_mai_2022_04.jpg"
  },
  {
    "imgPath": "./img/12_mai_2022/12_mai_2022_05.jpg"
  },
  {
    "imgPath": "./img/12_mai_2022/12_mai_2022_06.jpg"
  },
  {
    "imgPath": "./img/12_mai_2022/12_mai_2022_07.jpg"
  },
  {
    "imgPath": "./img/12_mai_2022/12_mai_2022_08.jpg"
  },
  {
    "imgPath": "./img/12_mai_2022/12_mai_2022_09.jpg"
  },
  {
    "imgPath": "./img/12_mai_2022/12_mai_2022_10.jpg"
  },
  {
    "imgPath": "./img/12_mai_2022/12_mai_2022_11.jpg"
  },
  {
    "imgPath": "./img/12_mai_2022/12_mai_2022_12.jpg"
  },
  {
    "imgPath": "./img/12_mai_2022/12_mai_2022_13.jpg"
  },
  {
    "imgPath": "./img/12_mai_2022/12_mai_2022_14.jpg"
  },
  {
    "imgPath": "./img/12_mai_2022/12_mai_2022_15.jpg"
  },
  {
    "imgPath": "./img/12_mai_2022/12_mai_2022_16.jpg"
  },
  {
    "imgPath": "./img/12_mai_2022/12_mai_2022_17.jpg"
  },
  {
    "imgPath": "./img/12_mai_2022/12_mai_2022_18.jpg"
  },
  {
    "imgPath": "./img/12_mai_2022/12_mai_2022_19.jpg"
  },
  {
    "imgPath": "./img/12_mai_2022/12_mai_2022_20.jpg"
  },
  {
    "imgPath": "./img/12_mai_2022/12_mai_2022_21.jpg"
  },
  {
    "imgPath": "./img/12_mai_2022/12_mai_2022_22.jpg"
  },
  {
    "imgPath": "./img/12_mai_2022/12_mai_2022_23.jpg"
  },
  {
    "imgPath": "./img/12_mai_2022/12_mai_2022_24.jpg"
  },
  {
    "imgPath": "./img/12_mai_2022/12_mai_2022_25.jpg"
  }
]
